nnue_parser-0.3.1.dist-info/METADATA
nnue_parser-0.3.1.dist-info/WHEEL
nnue_parser/__init__.py
nnue_parser/nnue_parser.cp311-win_amd64.pyd
nnue_parser-0.3.1.dist-info/RECORD
