Metadata-Version: 2.4
Name: nnue_parser
Version: 0.3.1
Summary: A fast NNUE-Parser for my NNUE implementation
Author: Jimmy Luong <nguyenhungjimmy.luong@gmail.com>
Author-email: Jimmy Luong <nguyenhungjimmy.luong@gmail.com>
License: MIT
Project-URL: Source Code, https://github.com/github-jimjim/NNUE-Parser
